{"set_name": "Unforgiven", "url": "/im/selectCard/series_id/659/goal/", "cards": [{"name": ["<strong>\"Cowboy\" Bob Orton Interferes</strong>"], "effect": ["<p>Randy Orton / Any Legend</p>"], "attributes": ["<li><strong>Card Type:</strong> Reversal</li>", "<li><strong>Collector's Number:</strong> 129</li>", "<li><strong>Rarity:</strong> Exclusive</li>", "<li><strong>Amount of Damage:</strong> 5</li>", "<li><strong>Fortitude:</strong> 15</li>"]}, {"name": ["<strong>\"Rowdy\" Roddy Piper</strong>"], "effect": ["<p>Piper</p>"], "attributes": ["<li><strong>Card Type:</strong> Superstar Card</li>", "<li><strong>Collector's Number:</strong> 124</li>", "<li><strong>Rarity:</strong> Exclusive</li>", "<li><strong>Hand size:</strong> 8</li>", "<li><strong>Superstar number:</strong> 5</li>"]}, {"name": ["<strong>2004 Diva Search Winner</strong>"], "effect": ["<p>Chrisy</p>"], "attributes": ["<li><strong>Card Type:</strong> Mid-match Action</li>", "<li><strong>Collector's Number:</strong> 114</li>", "<li><strong>Rarity:</strong> Ultra Rare</li>", "<li><strong>Amount of Damage:</strong> 0</li>", "<li><strong>Fortitude:</strong> 0</li>"]}, {"name": ["<strong>A Friendly Boot</strong>"], "effect": ["<p>Heidenreich</p>"], "attributes": ["<li><strong>Card Type:</strong> Strike</li>", "<li><strong>Collector's Number:</strong> 140</li>", "<li><strong>Rarity:</strong> Premium Rare</li>", "<li><strong>Amount of Damage:</strong> 15</li>", "<li><strong>Fortitude:</strong> 15</li>"]}, {"name": ["<strong>A Revolution of the Mind</strong>"], "effect": ["<p></p>"], "attributes": ["<li><strong>Card Type:</strong> Reversal</li>", "<li><strong>Collector's Number:</strong> 57</li>", "<li><strong>Rarity:</strong> Rare</li>", "<li><strong>Amount of Damage:</strong> 1</li>", "<li><strong>Fortitude:</strong> 0</li>"]}, {"name": ["<strong>A-List Attack</strong>"], "effect": ["<p>MNM</p>"], "attributes": ["<li><strong>Card Type:</strong> High Risk</li>", "<li><strong>Collector's Number:</strong> 152</li>", "<li><strong>Rarity:</strong> Premium Rare</li>", "<li><strong>Amount of Damage:</strong> 15</li>", "<li><strong>Fortitude:</strong> 10</li>"]}, {"name": ["<strong>Addicted to the Heat</strong>"], "effect": ["<p>Eddie Guerrero</p>"], "attributes": ["<li><strong>Card Type:</strong> Reversal</li>", "<li><strong>Collector's Number:</strong> 167</li>", "<li><strong>Rarity:</strong> Premium Rare</li>", "<li><strong>Amount of Damage:</strong> 0</li>", "<li><strong>Fortitude:</strong> 6</li>"]}, {"name": ["<strong>Afterburn</strong>"], "effect": ["<p></p>"], "attributes": ["<li><strong>Card Type:</strong> Action</li>", "<li><strong>Collector's Number:</strong> 64</li>", "<li><strong>Rarity:</strong> Uncommon</li>", "<li><strong>Amount of Damage:</strong> 1</li>", "<li><strong>Fortitude:</strong> 0</li>"]}, {"name": ["<strong>Ain't It Fair?</strong>"], "effect": ["<p>Christy</p>"], "attributes": ["<li><strong>Card Type:</strong> Action</li>", "<li><strong>Collector's Number:</strong> 115</li>", "<li><strong>Rarity:</strong> Exclusive</li>", "<li><strong>Amount of Damage:</strong> 0</li>", "<li><strong>Fortitude:</strong> 0</li>"]}, {"name": ["<strong>Another Big Freak'n Hellfire Boot</strong>"], "effect": ["<p>Kane</p>"], "attributes": ["<li><strong>Card Type:</strong> Strike</li>", "<li><strong>Collector's Number:</strong> 164</li>", "<li><strong>Rarity:</strong> Premium Rare</li>", "<li><strong>Amount of Damage:</strong> 6</li>", "<li><strong>Fortitude:</strong> 0</li>"]}, {"name": ["<strong>Ap Chaki Kick</strong>"], "effect": ["<p></p>"], "attributes": ["<li><strong>Card Type:</strong> Strike / Special</li>", "<li><strong>Collector's Number:</strong> 17</li>", "<li><strong>Rarity:</strong> Rare</li>", "<li><strong>Amount of Damage:</strong> 5</li>", "<li><strong>Fortitude:</strong> 5</li>"]}, {"name": ["<strong>Arm Stretch</strong>"], "effect": ["<p></p>"], "attributes": ["<li><strong>Card Type:</strong> Submission</li>", "<li><strong>Collector's Number:</strong> 46</li>", "<li><strong>Rarity:</strong> Uncommon</li>", "<li><strong>Amount of Damage:</strong> 8</li>", "<li><strong>Fortitude:</strong> 3</li>"]}, {"name": ["<strong>Baby Carriage</strong>"], "effect": ["<p>Gene Snitsky</p>"], "attributes": ["<li><strong>Card Type:</strong> Pre-match Object</li>", "<li><strong>Collector's Number:</strong> 143</li>", "<li><strong>Rarity:</strong> Ultra Rare</li>", "<li><strong>Amount of Damage:</strong> 0</li>", "<li><strong>Fortitude:</strong> 0</li>"]}, {"name": ["<strong>Back Body Drop TB</strong>"], "effect": ["<p></p>"], "attributes": ["<li><strong>Card Type:</strong> Strike / Special</li>", "<li><strong>Collector's Number:</strong> 14</li>", "<li><strong>Rarity:</strong> Uncommon</li>", "<li><strong>Amount of Damage:</strong> 12</li>", "<li><strong>Fortitude:</strong> 10</li>"]}, {"name": ["<strong>Back Fist TB</strong>"], "effect": ["<p></p>"], "attributes": ["<li><strong>Card Type:</strong> Strike / Special</li>", "<li><strong>Collector's Number:</strong> 13</li>", "<li><strong>Rarity:</strong> Uncommon</li>", "<li><strong>Amount of Damage:</strong> 4</li>", "<li><strong>Fortitude:</strong> 6</li>"]}, {"name": ["<strong>Backstage Shenanigans</strong>"], "effect": ["<p></p>"], "attributes": ["<li><strong>Card Type:</strong> Pre-match Event / Mid-match Action</li>", "<li><strong>Collector's Number:</strong> 81</li>", "<li><strong>Rarity:</strong> Uncommon</li>", "<li><strong>Amount of Damage:</strong> 0</li>", "<li><strong>Fortitude:</strong> 0</li>"]}, {"name": ["<strong>Bagpipe Introduction</strong>"], "effect": ["<p>Piper</p>"], "attributes": ["<li><strong>Card Type:</strong> Pre-match Event</li>", "<li><strong>Collector's Number:</strong> 125</li>", "<li><strong>Rarity:</strong> Ultra Rare</li>", "<li><strong>Amount of Damage:</strong> 0</li>", "<li><strong>Fortitude:</strong> 0</li>"]}, {"name": ["<strong>Baseball Slide TB</strong>"], "effect": ["<p></p>"], "attributes": ["<li><strong>Card Type:</strong> Strike / Special</li>", "<li><strong>Collector's Number:</strong> 19</li>", "<li><strong>Rarity:</strong> Rare</li>", "<li><strong>Amount of Damage:</strong> 15</li>", "<li><strong>Fortitude:</strong> 15</li>"]}, {"name": ["<strong>Batista</strong>"], "effect": ["<p>Batista</p>"], "attributes": ["<li><strong>Card Type:</strong> Superstar Card</li>", "<li><strong>Collector's Number:</strong> 100</li>", "<li><strong>Rarity:</strong> Exclusive</li>", "<li><strong>Hand size:</strong> 8</li>", "<li><strong>Superstar number:</strong> 3</li>"]}, {"name": ["<strong>Batista Bomb</strong>"], "effect": ["<p>Batista </p>", "<p><em>Trademark Finisher / Action</em></p>"], "attributes": ["<li><strong>Card Type:</strong> Trademark Finisher</li>", "<li><strong>Collector's Number:</strong> 102</li>", "<li><strong>Rarity:</strong> Ultra Rare</li>", "<li><strong>Amount of Damage:</strong> 40</li>", "<li><strong>Fortitude:</strong> 40</li>"]}, {"name": ["<strong>Batista's Spinebuster</strong>"], "effect": ["<p>Batista</p>"], "attributes": ["<li><strong>Card Type:</strong> Grapple / Special</li>", "<li><strong>Collector's Number:</strong> 105</li>", "<li><strong>Rarity:</strong> Exclusive</li>", "<li><strong>Amount of Damage:</strong> 15</li>", "<li><strong>Fortitude:</strong> 25</li>"]}, {"name": ["<strong>Bear Hug TB</strong>"], "effect": ["<p></p>"], "attributes": ["<li><strong>Card Type:</strong> Submission</li>", "<li><strong>Collector's Number:</strong> 41</li>", "<li><strong>Rarity:</strong> Common</li>", "<li><strong>Amount of Damage:</strong> 5</li>", "<li><strong>Fortitude:</strong> 1</li>"]}, {"name": ["<strong>Big Show's F5</strong>"], "effect": ["<p>Big Show</p>"], "attributes": ["<li><strong>Card Type:</strong> Mid-match Trademark Finisher / Special</li>", "<li><strong>Collector's Number:</strong> 170</li>", "<li><strong>Rarity:</strong> Premium Rare</li>", "<li><strong>Amount of Damage:</strong> 12</li>", "<li><strong>Fortitude:</strong> 25</li>"]}, {"name": ["<strong>Blindsided Precision</strong>"], "effect": ["<p></p>"], "attributes": ["<li><strong>Card Type:</strong> Pre-match Event</li>", "<li><strong>Collector's Number:</strong> 80</li>", "<li><strong>Rarity:</strong> Uncommon</li>", "<li><strong>Amount of Damage:</strong> 0</li>", "<li><strong>Fortitude:</strong> 0</li>"]}, {"name": ["<strong>Body Block</strong>"], "effect": ["<p></p>"], "attributes": ["<li><strong>Card Type:</strong> High Risk / Special</li>", "<li><strong>Collector's Number:</strong> 3</li>", "<li><strong>Rarity:</strong> Common</li>", "<li><strong>Amount of Damage:</strong> 7</li>", "<li><strong>Fortitude:</strong> 5</li>"]}, {"name": ["<strong>Booker's Thrust Kick</strong>"], "effect": ["<p>Booker T</p>"], "attributes": ["<li><strong>Card Type:</strong> Strike</li>", "<li><strong>Collector's Number:</strong> 173</li>", "<li><strong>Rarity:</strong> Premium Rare</li>", "<li><strong>Amount of Damage:</strong> 5</li>", "<li><strong>Fortitude:</strong> 0</li>"]}, {"name": ["<strong>Boston Crab TB</strong>"], "effect": ["<p></p>"], "attributes": ["<li><strong>Card Type:</strong> Submission</li>", "<li><strong>Collector's Number:</strong> 51</li>", "<li><strong>Rarity:</strong> Rare</li>", "<li><strong>Amount of Damage:</strong> 9</li>", "<li><strong>Fortitude:</strong> 9</li>"]}, {"name": ["<strong>Bow &amp; Arrow TB</strong>"], "effect": ["<p></p>"], "attributes": ["<li><strong>Card Type:</strong> Submission</li>", "<li><strong>Collector's Number:</strong> 43</li>", "<li><strong>Rarity:</strong> Common</li>", "<li><strong>Amount of Damage:</strong> 8</li>", "<li><strong>Fortitude:</strong> 5</li>"]}, {"name": ["<strong>Build Momentum</strong>"], "effect": ["<p></p>"], "attributes": ["<li><strong>Card Type:</strong> Action</li>", "<li><strong>Collector's Number:</strong> 58</li>", "<li><strong>Rarity:</strong> Common</li>", "<li><strong>Amount of Damage:</strong> 0</li>", "<li><strong>Fortitude:</strong> 0</li>"]}, {"name": ["<strong>Camel Clutch TB</strong>"], "effect": ["<p></p>"], "attributes": ["<li><strong>Card Type:</strong> Submission</li>", "<li><strong>Collector's Number:</strong> 49</li>", "<li><strong>Rarity:</strong> Uncommon</li>", "<li><strong>Amount of Damage:</strong> 8</li>", "<li><strong>Fortitude:</strong> 7</li>"]}, {"name": ["<strong>Candice: Internet Icon</strong>"], "effect": ["<p></p>"], "attributes": ["<li><strong>Card Type:</strong> Action</li>", "<li><strong>Collector's Number:</strong> 75</li>", "<li><strong>Rarity:</strong> Rare</li>", "<li><strong>Amount of Damage:</strong> 0</li>", "<li><strong>Fortitude:</strong> 10</li>"]}, {"name": ["<strong>Choke Hold TB</strong>"], "effect": ["<p></p>"], "attributes": ["<li><strong>Card Type:</strong> Submission</li>", "<li><strong>Collector's Number:</strong> 54</li>", "<li><strong>Rarity:</strong> Rare</li>", "<li><strong>Amount of Damage:</strong> 6</li>", "<li><strong>Fortitude:</strong> 0</li>"]}, {"name": ["<strong>Chris Jericho</strong>"], "effect": ["<p>Chris Jericho</p>"], "attributes": ["<li><strong>Card Type:</strong> Backstage Area</li>", "<li><strong>Collector's Number:</strong> 165</li>", "<li><strong>Rarity:</strong> Premium Rare</li>"]}, {"name": ["<strong>Christy</strong>"], "effect": ["<p>Christy</p>"], "attributes": ["<li><strong>Card Type:</strong> Superstar Card</li>", "<li><strong>Collector's Number:</strong> 112</li>", "<li><strong>Rarity:</strong> Exclusive</li>", "<li><strong>Hand size:</strong> 5</li>", "<li><strong>Superstar number:</strong> 2</li>"]}, {"name": ["<strong>Christy's Twist</strong>"], "effect": ["<p>Christy </p>", "<p><em>Trademark Finisher / Action</em></p>"], "attributes": ["<li><strong>Card Type:</strong> Trademark Finisher</li>", "<li><strong>Collector's Number:</strong> 116</li>", "<li><strong>Rarity:</strong> Exclusive</li>", "<li><strong>Amount of Damage:</strong> 7</li>", "<li><strong>Fortitude:</strong> 5</li>"]}, {"name": ["<strong>Christy: Curvy Cutie</strong>"], "effect": ["<p></p>"], "attributes": ["<li><strong>Card Type:</strong> Action</li>", "<li><strong>Collector's Number:</strong> 72</li>", "<li><strong>Rarity:</strong> Rare</li>", "<li><strong>Amount of Damage:</strong> 0</li>", "<li><strong>Fortitude:</strong> 4</li>"]}, {"name": ["<strong>Corkscrew Elbow</strong>"], "effect": ["<p></p>"], "attributes": ["<li><strong>Card Type:</strong> High Risk</li>", "<li><strong>Collector's Number:</strong> 2</li>", "<li><strong>Rarity:</strong> Common</li>", "<li><strong>Amount of Damage:</strong> 14</li>", "<li><strong>Fortitude:</strong> 11</li>"]}, {"name": ["<strong>Counter Slash</strong>"], "effect": ["<p></p>"], "attributes": ["<li><strong>Card Type:</strong> High Risk</li>", "<li><strong>Collector's Number:</strong> 1</li>", "<li><strong>Rarity:</strong> Common</li>", "<li><strong>Amount of Damage:</strong> 2</li>", "<li><strong>Fortitude:</strong> 0</li>"]}, {"name": ["<strong>Daddy's Little Girl TB</strong>"], "effect": ["<p>Stephanie McMahon</p>"], "attributes": ["<li><strong>Card Type:</strong> Action</li>", "<li><strong>Collector's Number:</strong> 182</li>", "<li><strong>Rarity:</strong> Premium Rare</li>", "<li><strong>Amount of Damage:</strong> 0</li>", "<li><strong>Fortitude:</strong> 5</li>"]}, {"name": ["<strong>Destiny</strong>"], "effect": ["<p>Randy Orton</p>"], "attributes": ["<li><strong>Card Type:</strong> Action</li>", "<li><strong>Collector's Number:</strong> 194</li>", "<li><strong>Rarity:</strong> Ultra Rare</li>", "<li><strong>Amount of Damage:</strong> 0</li>", "<li><strong>Fortitude:</strong> 0</li>"]}, {"name": ["<strong>Disasterpiece</strong>"], "effect": ["<p>Heidenreich</p>"], "attributes": ["<li><strong>Card Type:</strong> Pre-match Object</li>", "<li><strong>Collector's Number:</strong> 137</li>", "<li><strong>Rarity:</strong> Ultra Rare</li>", "<li><strong>Amount of Damage:</strong> 0</li>", "<li><strong>Fortitude:</strong> 0</li>"]}, {"name": ["<strong>Edge's Running Spear</strong>"], "effect": ["<p>Edge </p>", "<p><em>Strike / Strike / Reversal</em></p>"], "attributes": ["<li><strong>Card Type:</strong> Strike / Special</li>", "<li><strong>Collector's Number:</strong> 169</li>", "<li><strong>Rarity:</strong> Premium Rare</li>", "<li><strong>Amount of Damage:</strong> 10</li>", "<li><strong>Fortitude:</strong> 40</li>"]}, {"name": ["<strong>Educated Hands</strong>"], "effect": ["<p>Tajiri</p>"], "attributes": ["<li><strong>Card Type:</strong> Pre-match Event</li>", "<li><strong>Collector's Number:</strong> 177</li>", "<li><strong>Rarity:</strong> Premium Rare</li>", "<li><strong>Amount of Damage:</strong> 0</li>", "<li><strong>Fortitude:</strong> 0</li>"]}, {"name": ["<strong>Everything and the Kitchen Sink</strong>"], "effect": ["<p></p>"], "attributes": ["<li><strong>Card Type:</strong> Strike</li>", "<li><strong>Collector's Number:</strong> 16</li>", "<li><strong>Rarity:</strong> Uncommon</li>", "<li><strong>Amount of Damage:</strong> 6</li>", "<li><strong>Fortitude:</strong> 14</li>"]}, {"name": ["<strong>Eviscerated by Viscera</strong>"], "effect": ["<p></p>"], "attributes": ["<li><strong>Card Type:</strong> Mid-match Action</li>", "<li><strong>Collector's Number:</strong> 94</li>", "<li><strong>Rarity:</strong> Uncommon</li>", "<li><strong>Amount of Damage:</strong> 0</li>", "<li><strong>Fortitude:</strong> 6</li>"]}, {"name": ["<strong>Fans Love an Underdog</strong>"], "effect": ["<p></p>"], "attributes": ["<li><strong>Card Type:</strong> Pre-match Event</li>", "<li><strong>Collector's Number:</strong> 84</li>", "<li><strong>Rarity:</strong> Rare</li>", "<li><strong>Amount of Damage:</strong> 0</li>", "<li><strong>Fortitude:</strong> 0</li>"]}, {"name": ["<strong>Feathered Boa</strong>"], "effect": ["<p>Hulk Hogan</p>"], "attributes": ["<li><strong>Card Type:</strong> Backstage Area</li>", "<li><strong>Collector's Number:</strong> 119</li>", "<li><strong>Rarity:</strong> Ultra Rare</li>"]}, {"name": ["<strong>Fight For the Rights of Every Man</strong>"], "effect": ["<p>Hulk Hogan</p>"], "attributes": ["<li><strong>Card Type:</strong> Action</li>", "<li><strong>Collector's Number:</strong> 122</li>", "<li><strong>Rarity:</strong> Exclusive</li>", "<li><strong>Amount of Damage:</strong> 0</li>", "<li><strong>Fortitude:</strong> 5</li>"]}, {"name": ["<strong>Finally...The Rock Has Come Back To...</strong>"], "effect": ["<p>Rock</p>"], "attributes": ["<li><strong>Card Type:</strong> Action</li>", "<li><strong>Collector's Number:</strong> 163</li>", "<li><strong>Rarity:</strong> Premium Rare</li>", "<li><strong>Amount of Damage:</strong> 0</li>", "<li><strong>Fortitude:</strong> 0</li>"]}, {"name": ["<strong>Five Knuckle Shuffle</strong>"], "effect": ["<p>John Cena</p>"], "attributes": ["<li><strong>Card Type:</strong> High Risk</li>", "<li><strong>Collector's Number:</strong> 183</li>", "<li><strong>Rarity:</strong> Premium Rare</li>", "<li><strong>Amount of Damage:</strong> 5</li>", "<li><strong>Fortitude:</strong> 5</li>"]}, {"name": ["<strong>Flair's Chop Block</strong>"], "effect": ["<p>Ric Flair</p>"], "attributes": ["<li><strong>Card Type:</strong> Strike / Strike</li>", "<li><strong>Collector's Number:</strong> 175</li>", "<li><strong>Rarity:</strong> Premium Rare</li>", "<li><strong>Amount of Damage:</strong> 4</li>", "<li><strong>Fortitude:</strong> 4</li>"]}, {"name": ["<strong>Flip</strong>"], "effect": ["<p></p>"], "attributes": ["<li><strong>Card Type:</strong> Grapple</li>", "<li><strong>Collector's Number:</strong> 24</li>", "<li><strong>Rarity:</strong> Common</li>", "<li><strong>Amount of Damage:</strong> 4</li>", "<li><strong>Fortitude:</strong> 3</li>"]}, {"name": ["<strong>Flying Forearm</strong>"], "effect": ["<p>Shawn Michaels </p>", "<p><em>Strike + High Risk / Reversal</em></p>"], "attributes": ["<li><strong>Card Type:</strong> Maneuver / Reversal</li>", "<li><strong>Collector's Number:</strong> 180</li>", "<li><strong>Rarity:</strong> Premium Rare</li>", "<li><strong>Amount of Damage:</strong> 8</li>", "<li><strong>Fortitude:</strong> 5</li>"]}, {"name": ["<strong>Forever</strong>"], "effect": ["<p>Rey Mysterio </p>", "<p><em>Action + Action / Reversal</em></p>"], "attributes": ["<li><strong>Card Type:</strong> Action / Reversal</li>", "<li><strong>Collector's Number:</strong> 179</li>", "<li><strong>Rarity:</strong> Premium Rare</li>", "<li><strong>Amount of Damage:</strong> 0</li>", "<li><strong>Fortitude:</strong> 3</li>"]}, {"name": ["<strong>Frankie Takes Hollywood</strong>"], "effect": ["<p></p>"], "attributes": ["<li><strong>Card Type:</strong> Pre-match Event</li>", "<li><strong>Collector's Number:</strong> 85</li>", "<li><strong>Rarity:</strong> Rare</li>", "<li><strong>Amount of Damage:</strong> 0</li>", "<li><strong>Fortitude:</strong> 0</li>"]}, {"name": ["<strong>Full Nelson Slam TB</strong>"], "effect": ["<p></p>"], "attributes": ["<li><strong>Card Type:</strong> Grapple</li>", "<li><strong>Collector's Number:</strong> 33</li>", "<li><strong>Rarity:</strong> Rare</li>", "<li><strong>Amount of Damage:</strong> 8</li>", "<li><strong>Fortitude:</strong> 0</li>"]}, {"name": ["<strong>Full Nelson TB</strong>"], "effect": ["<p></p>"], "attributes": ["<li><strong>Card Type:</strong> Submission</li>", "<li><strong>Collector's Number:</strong> 42</li>", "<li><strong>Rarity:</strong> Common</li>", "<li><strong>Amount of Damage:</strong> 5</li>", "<li><strong>Fortitude:</strong> 2</li>"]}, {"name": ["<strong>Gene Snitsky</strong>"], "effect": ["<p>Gene Snitsky</p>"], "attributes": ["<li><strong>Card Type:</strong> Superstar Card</li>", "<li><strong>Collector's Number:</strong> 142</li>", "<li><strong>Rarity:</strong> Premium Rare</li>", "<li><strong>Hand size:</strong> 7</li>", "<li><strong>Superstar number:</strong> 1</li>"]}, {"name": ["<strong>Gentlemen's Establishment</strong>"], "effect": ["<p>Evolution / HHH / Ric Flair</p>"], "attributes": ["<li><strong>Card Type:</strong> Pre-Match Venue</li>", "<li><strong>Collector's Number:</strong> 191</li>", "<li><strong>Rarity:</strong> Ultra Rare</li>", "<li><strong>Amount of Damage:</strong> 0</li>", "<li><strong>Fortitude:</strong> 0</li>"]}, {"name": ["<strong>German Suplex TB</strong>"], "effect": ["<p></p>"], "attributes": ["<li><strong>Card Type:</strong> Grapple</li>", "<li><strong>Collector's Number:</strong> 35</li>", "<li><strong>Rarity:</strong> Rare</li>", "<li><strong>Amount of Damage:</strong> 8</li>", "<li><strong>Fortitude:</strong> 4</li>"]}, {"name": ["<strong>Girly Grab</strong>"], "effect": ["<p></p>"], "attributes": ["<li><strong>Card Type:</strong> Submission</li>", "<li><strong>Collector's Number:</strong> 187</li>", "<li><strong>Rarity:</strong> Premium Rare</li>", "<li><strong>Amount of Damage:</strong> 2</li>", "<li><strong>Fortitude:</strong> 0</li>"]}, {"name": ["<strong>Girly Slap</strong>"], "effect": ["<p></p>"], "attributes": ["<li><strong>Card Type:</strong> Strike</li>", "<li><strong>Collector's Number:</strong> 7</li>", "<li><strong>Rarity:</strong> Common</li>", "<li><strong>Amount of Damage:</strong> 1</li>", "<li><strong>Fortitude:</strong> 0</li>"]}, {"name": ["<strong>Grab WWE Timekeeper Mark Yeaton's Chair</strong>"], "effect": ["<p></p>"], "attributes": ["<li><strong>Card Type:</strong> Action</li>", "<li><strong>Collector's Number:</strong> 69</li>", "<li><strong>Rarity:</strong> Uncommon</li>", "<li><strong>Amount of Damage:</strong> 0</li>", "<li><strong>Fortitude:</strong> 5</li>"]}, {"name": ["<strong>Greetings, Citizen</strong>"], "effect": ["<p>Hurri-Friends </p>", "<p><em>Set-Up</em></p>"], "attributes": ["<li><strong>Card Type:</strong> Action</li>", "<li><strong>Collector's Number:</strong> 158</li>", "<li><strong>Rarity:</strong> Premium Rare</li>", "<li><strong>Amount of Damage:</strong> 0</li>", "<li><strong>Fortitude:</strong> 0</li>"]}, {"name": ["<strong>Guillotine Stretch TB</strong>"], "effect": ["<p></p>"], "attributes": ["<li><strong>Card Type:</strong> Submission</li>", "<li><strong>Collector's Number:</strong> 44</li>", "<li><strong>Rarity:</strong> Common</li>", "<li><strong>Amount of Damage:</strong> 8</li>", "<li><strong>Fortitude:</strong> 8</li>"]}, {"name": ["<strong>Hardcore Originator of ECW</strong>"], "effect": ["<p>Paul Heyman</p>"], "attributes": ["<li><strong>Card Type:</strong> Pre-match Event</li>", "<li><strong>Collector's Number:</strong> 192</li>", "<li><strong>Rarity:</strong> Ultra Rare</li>", "<li><strong>Amount of Damage:</strong> 0</li>", "<li><strong>Fortitude:</strong> 0</li>"]}, {"name": ["<strong>Hardcore Timekeeper's Bell</strong>"], "effect": ["<p></p>"], "attributes": ["<li><strong>Card Type:</strong> Action</li>", "<li><strong>Collector's Number:</strong> 62</li>", "<li><strong>Rarity:</strong> Common</li>", "<li><strong>Amount of Damage:</strong> 0</li>", "<li><strong>Fortitude:</strong> 2</li>"]}, {"name": ["<strong>Haterade</strong>"], "effect": ["<p>Teddy Long</p>"], "attributes": ["<li><strong>Card Type:</strong> Pre-match Object</li>", "<li><strong>Collector's Number:</strong> 131</li>", "<li><strong>Rarity:</strong> Ultra Rare</li>", "<li><strong>Amount of Damage:</strong> 0</li>", "<li><strong>Fortitude:</strong> 0</li>"]}, {"name": ["<strong>Headlock Takedown TB</strong>"], "effect": ["<p></p>"], "attributes": ["<li><strong>Card Type:</strong> Grapple</li>", "<li><strong>Collector's Number:</strong> 28</li>", "<li><strong>Rarity:</strong> Uncommon</li>", "<li><strong>Amount of Damage:</strong> 1</li>", "<li><strong>Fortitude:</strong> 0</li>"]}, {"name": ["<strong>Heidenreich</strong>"], "effect": ["<p>Heidenreich</p>"], "attributes": ["<li><strong>Card Type:</strong> Superstar Card</li>", "<li><strong>Collector's Number:</strong> 136</li>", "<li><strong>Rarity:</strong> Premium Rare</li>", "<li><strong>Hand size:</strong> 6</li>", "<li><strong>Superstar number:</strong> 1</li>"]}, {"name": ["<strong>Heidenreich's Elbow Drop</strong>"], "effect": ["<p>Heidenreich</p>"], "attributes": ["<li><strong>Card Type:</strong> High Risk</li>", "<li><strong>Collector's Number:</strong> 138</li>", "<li><strong>Rarity:</strong> Premium Rare</li>", "<li><strong>Amount of Damage:</strong> 8</li>", "<li><strong>Fortitude:</strong> 7</li>"]}, {"name": ["<strong>Hello, Ladies!</strong>"], "effect": ["<p></p>"], "attributes": ["<li><strong>Card Type:</strong> Pre-match Event</li>", "<li><strong>Collector's Number:</strong> 76</li>", "<li><strong>Rarity:</strong> Common</li>", "<li><strong>Amount of Damage:</strong> 0</li>", "<li><strong>Fortitude:</strong> 0</li>"]}, {"name": ["<strong>Hello, My Name is Eugene</strong>"], "effect": ["<p>Eugene</p>"], "attributes": ["<li><strong>Card Type:</strong> Action</li>", "<li><strong>Collector's Number:</strong> 197</li>", "<li><strong>Rarity:</strong> Ultra Rare</li>", "<li><strong>Amount of Damage:</strong> 0</li>", "<li><strong>Fortitude:</strong> 0</li>"]}, {"name": ["<strong>Here Comes the Money! TB</strong>"], "effect": ["<p>Shane O'Mac </p>", "<p><em>Mid-Match Action / Action / Reversal</em></p>"], "attributes": ["<li><strong>Card Type:</strong> Mid-match Action / Reversal</li>", "<li><strong>Collector's Number:</strong> 195</li>", "<li><strong>Rarity:</strong> Ultra Rare</li>", "<li><strong>Amount of Damage:</strong> 0</li>", "<li><strong>Fortitude:</strong> 0</li>"]}, {"name": ["<strong>Here I Stand: the Champion</strong>"], "effect": ["<p></p>"], "attributes": ["<li><strong>Card Type:</strong> Mid-match Action</li>", "<li><strong>Collector's Number:</strong> 92</li>", "<li><strong>Rarity:</strong> Uncommon</li>", "<li><strong>Amount of Damage:</strong> 0</li>", "<li><strong>Fortitude:</strong> 0</li>"]}, {"name": ["<strong>Hogan's Patented Overhand Punch</strong>"], "effect": ["<p>Hulk Hogan</p>"], "attributes": ["<li><strong>Card Type:</strong> Strike / Strike</li>", "<li><strong>Collector's Number:</strong> 121</li>", "<li><strong>Rarity:</strong> Exclusive</li>", "<li><strong>Amount of Damage:</strong> 5</li>", "<li><strong>Fortitude:</strong> 0</li>"]}, {"name": ["<strong>Holla! Holla! Holla!</strong>"], "effect": ["<p>Teddy Long </p>", "<p><em>Trademark Finisher + Action</em></p>"], "attributes": ["<li><strong>Card Type:</strong> Trademark Finisher</li>", "<li><strong>Collector's Number:</strong> 132</li>", "<li><strong>Rarity:</strong> Ultra Rare</li>", "<li><strong>Amount of Damage:</strong> 10</li>", "<li><strong>Fortitude:</strong> 10</li>"]}, {"name": ["<strong>Hot Rod</strong>"], "effect": ["<p>Piper</p>"], "attributes": ["<li><strong>Card Type:</strong> Action</li>", "<li><strong>Collector's Number:</strong> 128</li>", "<li><strong>Rarity:</strong> Exclusive</li>", "<li><strong>Amount of Damage:</strong> 0</li>", "<li><strong>Fortitude:</strong> 2</li>"]}, {"name": ["<strong>Hurri-Friends</strong>"], "effect": ["<p>Hurri-Friends</p>"], "attributes": ["<li><strong>Card Type:</strong> Superstar Card</li>", "<li><strong>Collector's Number:</strong> 154</li>", "<li><strong>Rarity:</strong> Premium Rare</li>", "<li><strong>Hand size:</strong> 3</li>", "<li><strong>Superstar number:</strong> 5</li>"]}, {"name": ["<strong>I am a Real American</strong>"], "effect": ["<p>Hulk Hogan</p>"], "attributes": ["<li><strong>Card Type:</strong> Pre-match Event</li>", "<li><strong>Collector's Number:</strong> 120</li>", "<li><strong>Rarity:</strong> Ultra Rare</li>", "<li><strong>Amount of Damage:</strong> 0</li>", "<li><strong>Fortitude:</strong> 0</li>"]}, {"name": ["<strong>I'm Just Hitting My Stride</strong>"], "effect": ["<p></p>"], "attributes": ["<li><strong>Card Type:</strong> Mid-match Action</li>", "<li><strong>Collector's Number:</strong> 96</li>", "<li><strong>Rarity:</strong> Rare</li>", "<li><strong>Amount of Damage:</strong> 0</li>", "<li><strong>Fortitude:</strong> 4</li>"]}, {"name": ["<strong>Immortal One</strong>"], "effect": ["<p>Hulk Hogan</p>"], "attributes": ["<li><strong>Card Type:</strong> Superstar Card</li>", "<li><strong>Collector's Number:</strong> 118</li>", "<li><strong>Rarity:</strong> Exclusive</li>", "<li><strong>Hand size:</strong> 9</li>", "<li><strong>Superstar number:</strong> 7</li>"]}, {"name": ["<strong>In My Day, a Maneuver was a Maneuver</strong>"], "effect": ["<p>Any Legend</p>"], "attributes": ["<li><strong>Card Type:</strong> Action / Reversal</li>", "<li><strong>Collector's Number:</strong> 123</li>", "<li><strong>Rarity:</strong> Exclusive</li>", "<li><strong>Amount of Damage:</strong> 0</li>", "<li><strong>Fortitude:</strong> 0</li>"]}, {"name": ["<strong>In This Ring, I Just Might Be...</strong>"], "effect": ["<p></p>"], "attributes": ["<li><strong>Card Type:</strong> Mid-match Action</li>", "<li><strong>Collector's Number:</strong> 97</li>", "<li><strong>Rarity:</strong> Rare</li>", "<li><strong>Amount of Damage:</strong> 0</li>", "<li><strong>Fortitude:</strong> 2</li>"]}, {"name": ["<strong>Incredible Athleticism</strong>"], "effect": ["<p>Shelton Benjamin</p>"], "attributes": ["<li><strong>Card Type:</strong> Action</li>", "<li><strong>Collector's Number:</strong> 196</li>", "<li><strong>Rarity:</strong> Ultra Rare</li>", "<li><strong>Amount of Damage:</strong> 0</li>", "<li><strong>Fortitude:</strong> 0</li>"]}, {"name": ["<strong>Inferno Match TB</strong>"], "effect": ["<p></p>"], "attributes": ["<li><strong>Card Type:</strong> Pre-match Event</li>", "<li><strong>Collector's Number:</strong> 86</li>", "<li><strong>Rarity:</strong> Rare</li>", "<li><strong>Amount of Damage:</strong> 0</li>", "<li><strong>Fortitude:</strong> 0</li>"]}, {"name": ["<strong>Introduce Your Brain to Your Mouth...</strong>"], "effect": ["<p></p>"], "attributes": ["<li><strong>Card Type:</strong> Mid-match Reversal</li>", "<li><strong>Collector's Number:</strong> 98</li>", "<li><strong>Rarity:</strong> Rare</li>", "<li><strong>Amount of Damage:</strong> 0</li>", "<li><strong>Fortitude:</strong> 20</li>"]}, {"name": ["<strong>It's Not My Fault</strong>"], "effect": ["<p>Gene Snitsky</p>"], "attributes": ["<li><strong>Card Type:</strong> Action</li>", "<li><strong>Collector's Number:</strong> 145</li>", "<li><strong>Rarity:</strong> Premium Rare</li>", "<li><strong>Amount of Damage:</strong> 0</li>", "<li><strong>Fortitude:</strong> 12</li>"]}, {"name": ["<strong>Japanese Arm Drag TB</strong>"], "effect": ["<p>Set-Up</p>"], "attributes": ["<li><strong>Card Type:</strong> Grapple</li>", "<li><strong>Collector's Number:</strong> 22</li>", "<li><strong>Rarity:</strong> Common</li>", "<li><strong>Amount of Damage:</strong> 2</li>", "<li><strong>Fortitude:</strong> 0</li>"]}, {"name": ["<strong>Just Close Your Eyes</strong>"], "effect": ["<p>Christian</p>"], "attributes": ["<li><strong>Card Type:</strong> Action / Reversal</li>", "<li><strong>Collector's Number:</strong> 108</li>", "<li><strong>Rarity:</strong> Ultra Rare</li>", "<li><strong>Amount of Damage:</strong> 7</li>", "<li><strong>Fortitude:</strong> 4</li>"]}, {"name": ["<strong>Kickin' It Old School</strong>"], "effect": ["<p></p>"], "attributes": ["<li><strong>Card Type:</strong> Action</li>", "<li><strong>Collector's Number:</strong> 66</li>", "<li><strong>Rarity:</strong> Uncommon</li>", "<li><strong>Amount of Damage:</strong> 0</li>", "<li><strong>Fortitude:</strong> 7</li>"]}, {"name": ["<strong>Kidney Punch</strong>"], "effect": ["<p></p>"], "attributes": ["<li><strong>Card Type:</strong> Strike</li>", "<li><strong>Collector's Number:</strong> 10</li>", "<li><strong>Rarity:</strong> Common</li>", "<li><strong>Amount of Damage:</strong> 8</li>", "<li><strong>Fortitude:</strong> 4</li>"]}, {"name": ["<strong>Knee Breaker TB</strong>"], "effect": ["<p></p>"], "attributes": ["<li><strong>Card Type:</strong> Strike</li>", "<li><strong>Collector's Number:</strong> 12</li>", "<li><strong>Rarity:</strong> Uncommon</li>", "<li><strong>Amount of Damage:</strong> 8</li>", "<li><strong>Fortitude:</strong> 1</li>"]}, {"name": ["<strong>Kurt Angle Invitational</strong>"], "effect": ["<p>Kurt Angle</p>"], "attributes": ["<li><strong>Card Type:</strong> Pre-match Stipulation</li>", "<li><strong>Collector's Number:</strong> 168</li>", "<li><strong>Rarity:</strong> Premium Rare</li>", "<li><strong>Amount of Damage:</strong> 0</li>", "<li><strong>Fortitude:</strong> 0</li>"]}, {"name": ["<strong>Le Bonsoir</strong>"], "effect": ["<p>Rene Dupree </p>", "<p><em>Trademark Finisher / Special / Action</em></p>"], "attributes": ["<li><strong>Card Type:</strong> Trademark Finisher / Special</li>", "<li><strong>Collector's Number:</strong> 198</li>", "<li><strong>Rarity:</strong> Ultra Rare</li>", "<li><strong>Amount of Damage:</strong> 20</li>", "<li><strong>Fortitude:</strong> 30</li>"]}, {"name": ["<strong>Leader of the Peepulation</strong>"], "effect": ["<p>Christian</p>"], "attributes": ["<li><strong>Card Type:</strong> Superstar Card</li>", "<li><strong>Collector's Number:</strong> 106</li>", "<li><strong>Rarity:</strong> Exclusive</li>", "<li><strong>Hand size:</strong> 6</li>", "<li><strong>Superstar number:</strong> 4</li>"]}, {"name": ["<strong>Lift a Boot TB</strong>"], "effect": ["<p></p>"], "attributes": ["<li><strong>Card Type:</strong> Reversal</li>", "<li><strong>Collector's Number:</strong> 55</li>", "<li><strong>Rarity:</strong> Common</li>", "<li><strong>Amount of Damage:</strong> 1</li>", "<li><strong>Fortitude:</strong> 0</li>"]}, {"name": ["<strong>Lilian: Amazing Announcer</strong>"], "effect": ["<p></p>"], "attributes": ["<li><strong>Card Type:</strong> Action</li>", "<li><strong>Collector's Number:</strong> 74</li>", "<li><strong>Rarity:</strong> Rare</li>", "<li><strong>Amount of Damage:</strong> 0</li>", "<li><strong>Fortitude:</strong> 8</li>"]}, {"name": ["<strong>Listen Loud and Clear</strong>"], "effect": ["<p></p>"], "attributes": ["<li><strong>Card Type:</strong> Action</li>", "<li><strong>Collector's Number:</strong> 61</li>", "<li><strong>Rarity:</strong> Common</li>", "<li><strong>Amount of Damage:</strong> 0</li>", "<li><strong>Fortitude:</strong> 3</li>"]}, {"name": ["<strong>Lock, Stock, and Barrel</strong>"], "effect": ["<p>Strike + Strike / Action + Action</p>"], "attributes": ["<li><strong>Card Type:</strong> Strike / Strike</li>", "<li><strong>Collector's Number:</strong> 20</li>", "<li><strong>Rarity:</strong> Rare</li>", "<li><strong>Amount of Damage:</strong> 14</li>", "<li><strong>Fortitude:</strong> 16</li>"]}, {"name": ["<strong>Making the Game</strong>"], "effect": ["<p>HHH</p>"], "attributes": ["<li><strong>Card Type:</strong> Action</li>", "<li><strong>Collector's Number:</strong> 162</li>", "<li><strong>Rarity:</strong> Premium Rare</li>", "<li><strong>Amount of Damage:</strong> 0</li>", "<li><strong>Fortitude:</strong> 11</li>"]}, {"name": ["<strong>Managed by Melina</strong>"], "effect": ["<p>MNM</p>"], "attributes": ["<li><strong>Card Type:</strong> Pre-match Manager</li>", "<li><strong>Collector's Number:</strong> 150</li>", "<li><strong>Rarity:</strong> Premium Rare</li>", "<li><strong>Amount of Damage:</strong> 0</li>", "<li><strong>Fortitude:</strong> 0</li>"]}, {"name": ["<strong>Managed by Stacy Keibler</strong>"], "effect": ["<p></p>"], "attributes": ["<li><strong>Card Type:</strong> Pre-match Manager</li>", "<li><strong>Collector's Number:</strong> 184</li>", "<li><strong>Rarity:</strong> Premium Rare</li>", "<li><strong>Amount of Damage:</strong> 0</li>", "<li><strong>Fortitude:</strong> 0</li>"]}, {"name": ["<strong>Managed by Tyson Tomko</strong>"], "effect": ["<p>Christian</p>"], "attributes": ["<li><strong>Card Type:</strong> Pre-match Manager</li>", "<li><strong>Collector's Number:</strong> 107</li>", "<li><strong>Rarity:</strong> Ultra Rare</li>", "<li><strong>Amount of Damage:</strong> 0</li>", "<li><strong>Fortitude:</strong> 0</li>"]}, {"name": ["<strong>Maria: Ideal Interviewer</strong>"], "effect": ["<p></p>"], "attributes": ["<li><strong>Card Type:</strong> Action</li>", "<li><strong>Collector's Number:</strong> 71</li>", "<li><strong>Rarity:</strong> Rare</li>", "<li><strong>Amount of Damage:</strong> 0</li>", "<li><strong>Fortitude:</strong> 2</li>"]}, {"name": ["<strong>Marking Out TB</strong>"], "effect": ["<p></p>"], "attributes": ["<li><strong>Card Type:</strong> Action</li>", "<li><strong>Collector's Number:</strong> 68</li>", "<li><strong>Rarity:</strong> Uncommon</li>", "<li><strong>Amount of Damage:</strong> 0</li>", "<li><strong>Fortitude:</strong> 0</li>"]}, {"name": ["<strong>McMahon-us Interrupt-us</strong>"], "effect": ["<p>Vince McMahon</p>"], "attributes": ["<li><strong>Card Type:</strong> Mid-match Reversal</li>", "<li><strong>Collector's Number:</strong> 190</li>", "<li><strong>Rarity:</strong> Ultra Rare</li>", "<li><strong>Amount of Damage:</strong> 0</li>", "<li><strong>Fortitude:</strong> 0</li>"]}, {"name": ["<strong>Melina Interferes</strong>"], "effect": ["<p>MNM</p>"], "attributes": ["<li><strong>Card Type:</strong> Reversal</li>", "<li><strong>Collector's Number:</strong> 153</li>", "<li><strong>Rarity:</strong> Premium Rare</li>", "<li><strong>Amount of Damage:</strong> 5</li>", "<li><strong>Fortitude:</strong> 25</li>"]}, {"name": ["<strong>Melina: Naughty Manager</strong>"], "effect": ["<p></p>"], "attributes": ["<li><strong>Card Type:</strong> Action</li>", "<li><strong>Collector's Number:</strong> 73</li>", "<li><strong>Rarity:</strong> Rare</li>", "<li><strong>Amount of Damage:</strong> 0</li>", "<li><strong>Fortitude:</strong> 6</li>"]}, {"name": ["<strong>Missile Dropkick TB</strong>"], "effect": ["<p></p>"], "attributes": ["<li><strong>Card Type:</strong> Action / High Risk</li>", "<li><strong>Collector's Number:</strong> 5</li>", "<li><strong>Rarity:</strong> Uncommon</li>", "<li><strong>Amount of Damage:</strong> 15</li>", "<li><strong>Fortitude:</strong> 15</li>"]}, {"name": ["<strong>MNM</strong>"], "effect": ["<p>MNM</p>"], "attributes": ["<li><strong>Card Type:</strong> Superstar Card</li>", "<li><strong>Collector's Number:</strong> 148</li>", "<li><strong>Rarity:</strong> Premium Rare</li>", "<li><strong>Hand size:</strong> 10</li>", "<li><strong>Superstar number:</strong> 2</li>"]}, {"name": ["<strong>Never Forgive - Never Forget</strong>"], "effect": ["<p>Batista / Christy / Gene Snitsky / Heidenreich / Leader of the Peepulation / MNM / \"Rowdy\" Roddy Piper / Smackdown! GM Theodore Long / The Hurri-Friends / The Immortal One</p>"], "attributes": ["<li><strong>Card Type:</strong> Action / Reversal</li>", "<li><strong>Collector's Number:</strong> 189</li>", "<li><strong>Rarity:</strong> Premium Rare</li>", "<li><strong>Amount of Damage:</strong> 0</li>", "<li><strong>Fortitude:</strong> 5</li>"]}, {"name": ["<strong>No Fault Clothesline</strong>"], "effect": ["<p>Gene Snitsky</p>"], "attributes": ["<li><strong>Card Type:</strong> Strike</li>", "<li><strong>Collector's Number:</strong> 146</li>", "<li><strong>Rarity:</strong> Premium Rare</li>", "<li><strong>Amount of Damage:</strong> 15</li>", "<li><strong>Fortitude:</strong> 15</li>"]}, {"name": ["<strong>No Fault Pump Handle Slam</strong>"], "effect": ["<p>Gene Snitsky</p>"], "attributes": ["<li><strong>Card Type:</strong> Trademark Finisher / Special</li>", "<li><strong>Collector's Number:</strong> 147</li>", "<li><strong>Rarity:</strong> Premium Rare</li>", "<li><strong>Amount of Damage:</strong> 25</li>", "<li><strong>Fortitude:</strong> 30</li>"]}, {"name": ["<strong>Nobody's Safe</strong>"], "effect": ["<p>Undertaker</p>"], "attributes": ["<li><strong>Card Type:</strong> Action</li>", "<li><strong>Collector's Number:</strong> 161</li>", "<li><strong>Rarity:</strong> Premium Rare</li>", "<li><strong>Amount of Damage:</strong> 0</li>", "<li><strong>Fortitude:</strong> 6</li>"]}, {"name": ["<strong>Not in Front of the Kids!</strong>"], "effect": ["<p></p>"], "attributes": ["<li><strong>Card Type:</strong> Mid-match Action</li>", "<li><strong>Collector's Number:</strong> 88</li>", "<li><strong>Rarity:</strong> Common</li>", "<li><strong>Amount of Damage:</strong> 0</li>", "<li><strong>Fortitude:</strong> 0</li>"]}, {"name": ["<strong>Not Yet TB</strong>"], "effect": ["<p></p>"], "attributes": ["<li><strong>Card Type:</strong> Action</li>", "<li><strong>Collector's Number:</strong> 63</li>", "<li><strong>Rarity:</strong> Common</li>", "<li><strong>Amount of Damage:</strong> 0</li>", "<li><strong>Fortitude:</strong> 0</li>"]}, {"name": ["<strong>One More Time - One Last Chance</strong>"], "effect": ["<p></p>"], "attributes": ["<li><strong>Card Type:</strong> Mid-match Action / Action</li>", "<li><strong>Collector's Number:</strong> 99</li>", "<li><strong>Rarity:</strong> Rare</li>", "<li><strong>Amount of Damage:</strong> 0</li>", "<li><strong>Fortitude:</strong> 20</li>"]}, {"name": ["<strong>Orlando Jordan: Chief of Staff</strong>"], "effect": ["<p>JBL</p>"], "attributes": ["<li><strong>Card Type:</strong> Pre-match Manager</li>", "<li><strong>Collector's Number:</strong> 193</li>", "<li><strong>Rarity:</strong> Ultra Rare</li>", "<li><strong>Amount of Damage:</strong> 0</li>", "<li><strong>Fortitude:</strong> 0</li>"]}, {"name": ["<strong>Over Sell: Hot Rod Style</strong>"], "effect": ["<p>Piper</p>"], "attributes": ["<li><strong>Card Type:</strong> Reversal</li>", "<li><strong>Collector's Number:</strong> 127</li>", "<li><strong>Rarity:</strong> Exclusive</li>", "<li><strong>Amount of Damage:</strong> 0</li>", "<li><strong>Fortitude:</strong> 0</li>"]}, {"name": ["<strong>Pendulum Back Breaker</strong>"], "effect": ["<p></p>"], "attributes": ["<li><strong>Card Type:</strong> Grapple</li>", "<li><strong>Collector's Number:</strong> 31</li>", "<li><strong>Rarity:</strong> Uncommon</li>", "<li><strong>Amount of Damage:</strong> 9</li>", "<li><strong>Fortitude:</strong> 9</li>"]}, {"name": ["<strong>Physically Dominant Force</strong>"], "effect": ["<p>Batista / Phenom</p>"], "attributes": ["<li><strong>Card Type:</strong> Reversal</li>", "<li><strong>Collector's Number:</strong> 104</li>", "<li><strong>Rarity:</strong> Exclusive</li>", "<li><strong>Amount of Damage:</strong> 0</li>", "<li><strong>Fortitude:</strong> 10</li>"]}, {"name": ["<strong>Piper's Pit</strong>"], "effect": ["<p>Piper</p>"], "attributes": ["<li><strong>Card Type:</strong> Pre-match Event</li>", "<li><strong>Collector's Number:</strong> 126</li>", "<li><strong>Rarity:</strong> Ultra Rare</li>", "<li><strong>Amount of Damage:</strong> 0</li>", "<li><strong>Fortitude:</strong> 0</li>"]}, {"name": ["<strong>Powerbomb TB</strong>"], "effect": ["<p></p>"], "attributes": ["<li><strong>Card Type:</strong> Grapple</li>", "<li><strong>Collector's Number:</strong> 32</li>", "<li><strong>Rarity:</strong> Uncommon</li>", "<li><strong>Amount of Damage:</strong> 13</li>", "<li><strong>Fortitude:</strong> 12</li>"]}, {"name": ["<strong>Precision Clothesline</strong>"], "effect": ["<p></p>"], "attributes": ["<li><strong>Card Type:</strong> Strike</li>", "<li><strong>Collector's Number:</strong> 18</li>", "<li><strong>Rarity:</strong> Rare</li>", "<li><strong>Amount of Damage:</strong> 8</li>", "<li><strong>Fortitude:</strong> 10</li>"]}, {"name": ["<strong>Precision Leg Lock</strong>"], "effect": ["<p></p>"], "attributes": ["<li><strong>Card Type:</strong> Submission</li>", "<li><strong>Collector's Number:</strong> 52</li>", "<li><strong>Rarity:</strong> Rare</li>", "<li><strong>Amount of Damage:</strong> 10</li>", "<li><strong>Fortitude:</strong> 10</li>"]}, {"name": ["<strong>Precision Power Slam</strong>"], "effect": ["<p></p>"], "attributes": ["<li><strong>Card Type:</strong> Grapple</li>", "<li><strong>Collector's Number:</strong> 39</li>", "<li><strong>Rarity:</strong> Rare</li>", "<li><strong>Amount of Damage:</strong> 14</li>", "<li><strong>Fortitude:</strong> 16</li>"]}, {"name": ["<strong>Pyrotechnic Volley</strong>"], "effect": ["<p></p>"], "attributes": ["<li><strong>Card Type:</strong> Pre-match Event</li>", "<li><strong>Collector's Number:</strong> 82</li>", "<li><strong>Rarity:</strong> Uncommon</li>", "<li><strong>Amount of Damage:</strong> 0</li>", "<li><strong>Fortitude:</strong> 0</li>"]}, {"name": ["<strong>Redheaded Sparkplug</strong>"], "effect": ["<p>Christy</p>"], "attributes": ["<li><strong>Card Type:</strong> Action</li>", "<li><strong>Collector's Number:</strong> 117</li>", "<li><strong>Rarity:</strong> Exclusive</li>", "<li><strong>Amount of Damage:</strong> 0</li>", "<li><strong>Fortitude:</strong> 5</li>"]}, {"name": ["<strong>Restricted Use in This Area</strong>"], "effect": ["<p></p>"], "attributes": ["<li><strong>Card Type:</strong> Mid-match Reversal</li>", "<li><strong>Collector's Number:</strong> 178</li>", "<li><strong>Rarity:</strong> Premium Rare</li>", "<li><strong>Amount of Damage:</strong> 0</li>", "<li><strong>Fortitude:</strong> 0</li>"]}, {"name": ["<strong>Reverse Clothesline</strong>"], "effect": ["<p></p>"], "attributes": ["<li><strong>Card Type:</strong> Strike / Special</li>", "<li><strong>Collector's Number:</strong> 15</li>", "<li><strong>Rarity:</strong> Uncommon</li>", "<li><strong>Amount of Damage:</strong> 8</li>", "<li><strong>Fortitude:</strong> 12</li>"]}, {"name": ["<strong>Rochester, New York</strong>"], "effect": ["<p></p>"], "attributes": ["<li><strong>Card Type:</strong> Pre-Match Venue</li>", "<li><strong>Collector's Number:</strong> 77</li>", "<li><strong>Rarity:</strong> Common</li>", "<li><strong>Amount of Damage:</strong> 0</li>", "<li><strong>Fortitude:</strong> 0</li>"]}, {"name": ["<strong>Rolling Hip Toss</strong>"], "effect": ["<p></p>"], "attributes": ["<li><strong>Card Type:</strong> Grapple</li>", "<li><strong>Collector's Number:</strong> 21</li>", "<li><strong>Rarity:</strong> Common</li>", "<li><strong>Amount of Damage:</strong> 3</li>", "<li><strong>Fortitude:</strong> 0</li>"]}, {"name": ["<strong>Running Elbow Smash TB</strong>"], "effect": ["<p></p>"], "attributes": ["<li><strong>Card Type:</strong> Strike</li>", "<li><strong>Collector's Number:</strong> 9</li>", "<li><strong>Rarity:</strong> Common</li>", "<li><strong>Amount of Damage:</strong> 8</li>", "<li><strong>Fortitude:</strong> 2</li>"]}, {"name": ["<strong>Running Shoulder Block</strong>"], "effect": ["<p>Heidenreich </p>", "<p><em>Strike / Strike / Reversal</em></p>"], "attributes": ["<li><strong>Card Type:</strong> Strike / Special</li>", "<li><strong>Collector's Number:</strong> 141</li>", "<li><strong>Rarity:</strong> Premium Rare</li>", "<li><strong>Amount of Damage:</strong> 25</li>", "<li><strong>Fortitude:</strong> 30</li>"]}, {"name": ["<strong>Running Spinebuster TB</strong>"], "effect": ["<p></p>"], "attributes": ["<li><strong>Card Type:</strong> Grapple</li>", "<li><strong>Collector's Number:</strong> 25</li>", "<li><strong>Rarity:</strong> Common</li>", "<li><strong>Amount of Damage:</strong> 7</li>", "<li><strong>Fortitude:</strong> 4</li>"]}, {"name": ["<strong>Shake It Off TB</strong>"], "effect": ["<p></p>"], "attributes": ["<li><strong>Card Type:</strong> Action</li>", "<li><strong>Collector's Number:</strong> 60</li>", "<li><strong>Rarity:</strong> Common</li>", "<li><strong>Amount of Damage:</strong> 0</li>", "<li><strong>Fortitude:</strong> 1</li>"]}, {"name": ["<strong>Sharmell: Sizzling Spouse</strong>"], "effect": ["<p></p>"], "attributes": ["<li><strong>Card Type:</strong> Action</li>", "<li><strong>Collector's Number:</strong> 70</li>", "<li><strong>Rarity:</strong> Rare</li>", "<li><strong>Amount of Damage:</strong> 0</li>", "<li><strong>Fortitude:</strong> 0</li>"]}, {"name": ["<strong>Shoot Russian Leg Sweep</strong>"], "effect": ["<p></p>"], "attributes": ["<li><strong>Card Type:</strong> Grapple</li>", "<li><strong>Collector's Number:</strong> 34</li>", "<li><strong>Rarity:</strong> Rare</li>", "<li><strong>Amount of Damage:</strong> 6</li>", "<li><strong>Fortitude:</strong> 0</li>"]}, {"name": ["<strong>Shoot Suplex</strong>"], "effect": ["<p></p>"], "attributes": ["<li><strong>Card Type:</strong> Grapple</li>", "<li><strong>Collector's Number:</strong> 26</li>", "<li><strong>Rarity:</strong> Common</li>", "<li><strong>Amount of Damage:</strong> 8</li>", "<li><strong>Fortitude:</strong> 6</li>"]}, {"name": ["<strong>Shooting Star Press TB</strong>"], "effect": ["<p></p>"], "attributes": ["<li><strong>Card Type:</strong> High Risk</li>", "<li><strong>Collector's Number:</strong> 6</li>", "<li><strong>Rarity:</strong> Uncommon</li>", "<li><strong>Amount of Damage:</strong> 20</li>", "<li><strong>Fortitude:</strong> 20</li>"]}, {"name": ["<strong>Shoulder Block TB</strong>"], "effect": ["<p></p>"], "attributes": ["<li><strong>Card Type:</strong> Strike</li>", "<li><strong>Collector's Number:</strong> 8</li>", "<li><strong>Rarity:</strong> Common</li>", "<li><strong>Amount of Damage:</strong> 2</li>", "<li><strong>Fortitude:</strong> 0</li>"]}, {"name": ["<strong>Side Chinlock</strong>"], "effect": ["<p></p>"], "attributes": ["<li><strong>Card Type:</strong> Submission</li>", "<li><strong>Collector's Number:</strong> 48</li>", "<li><strong>Rarity:</strong> Uncommon</li>", "<li><strong>Amount of Damage:</strong> 8</li>", "<li><strong>Fortitude:</strong> 5</li>"]}, {"name": ["<strong>Side Headlock</strong>"], "effect": ["<p></p>"], "attributes": ["<li><strong>Card Type:</strong> Submission</li>", "<li><strong>Collector's Number:</strong> 40</li>", "<li><strong>Rarity:</strong> Common</li>", "<li><strong>Amount of Damage:</strong> 2</li>", "<li><strong>Fortitude:</strong> 0</li>"]}, {"name": ["<strong>Sidewalk Slam TB</strong>"], "effect": ["<p></p>"], "attributes": ["<li><strong>Card Type:</strong> Grapple / Special</li>", "<li><strong>Collector's Number:</strong> 23</li>", "<li><strong>Rarity:</strong> Common</li>", "<li><strong>Amount of Damage:</strong> 3</li>", "<li><strong>Fortitude:</strong> 0</li>"]}, {"name": ["<strong>Sit Out Powerbomb TB</strong>"], "effect": ["<p></p>"], "attributes": ["<li><strong>Card Type:</strong> Grapple</li>", "<li><strong>Collector's Number:</strong> 36</li>", "<li><strong>Rarity:</strong> Rare</li>", "<li><strong>Amount of Damage:</strong> 10</li>", "<li><strong>Fortitude:</strong> 7</li>"]}, {"name": ["<strong>Sleeper TB</strong>"], "effect": ["<p></p>"], "attributes": ["<li><strong>Card Type:</strong> Submission</li>", "<li><strong>Collector's Number:</strong> 47</li>", "<li><strong>Rarity:</strong> Uncommon</li>", "<li><strong>Amount of Damage:</strong> 6</li>", "<li><strong>Fortitude:</strong> 4</li>"]}, {"name": ["<strong>Smackdown! GM Theodore Long</strong>"], "effect": ["<p>Teddy Long</p>"], "attributes": ["<li><strong>Card Type:</strong> Superstar Card</li>", "<li><strong>Collector's Number:</strong> 130</li>", "<li><strong>Rarity:</strong> Exclusive</li>", "<li><strong>Amount of Damage:</strong> 1</li>", "<li><strong>Fortitude:</strong> 0</li>"]}, {"name": ["<strong>Small Package TB</strong>"], "effect": ["<p></p>"], "attributes": ["<li><strong>Card Type:</strong> Grapple</li>", "<li><strong>Collector's Number:</strong> 29</li>", "<li><strong>Rarity:</strong> Uncommon</li>", "<li><strong>Amount of Damage:</strong> 1</li>", "<li><strong>Fortitude:</strong> 3</li>"]}, {"name": ["<strong>Snap Suplex TB</strong>"], "effect": ["<p></p>"], "attributes": ["<li><strong>Card Type:</strong> Grapple</li>", "<li><strong>Collector's Number:</strong> 27</li>", "<li><strong>Rarity:</strong> Uncommon</li>", "<li><strong>Amount of Damage:</strong> 5</li>", "<li><strong>Fortitude:</strong> 0</li>"]}, {"name": ["<strong>Spider Web Moonsault</strong>"], "effect": ["<p>Victoria</p>"], "attributes": ["<li><strong>Card Type:</strong> Action / High Risk</li>", "<li><strong>Collector's Number:</strong> 186</li>", "<li><strong>Rarity:</strong> Premium Rare</li>", "<li><strong>Amount of Damage:</strong> 5</li>", "<li><strong>Fortitude:</strong> 0</li>"]}, {"name": ["<strong>Spinning Leg Drop</strong>"], "effect": ["<p></p>"], "attributes": ["<li><strong>Card Type:</strong> High Risk</li>", "<li><strong>Collector's Number:</strong> 4</li>", "<li><strong>Rarity:</strong> Common</li>", "<li><strong>Amount of Damage:</strong> 9</li>", "<li><strong>Fortitude:</strong> 4</li>"]}, {"name": ["<strong>Spinning Toe Hold</strong>"], "effect": ["<p></p>"], "attributes": ["<li><strong>Card Type:</strong> Submission</li>", "<li><strong>Collector's Number:</strong> 50</li>", "<li><strong>Rarity:</strong> Rare</li>", "<li><strong>Amount of Damage:</strong> 8</li>", "<li><strong>Fortitude:</strong> 4</li>"]}, {"name": ["<strong>Spot Adjustment</strong>"], "effect": ["<p></p>"], "attributes": ["<li><strong>Card Type:</strong> Reversal</li>", "<li><strong>Collector's Number:</strong> 56</li>", "<li><strong>Rarity:</strong> Uncommon</li>", "<li><strong>Amount of Damage:</strong> 0</li>", "<li><strong>Fortitude:</strong> 1</li>"]}, {"name": ["<strong>Stacy's Roundhouse Kick</strong>"], "effect": ["<p>Stacy Keibler</p>"], "attributes": ["<li><strong>Card Type:</strong> Trademark Finisher / Special</li>", "<li><strong>Collector's Number:</strong> 159</li>", "<li><strong>Rarity:</strong> Premium Rare</li>", "<li><strong>Amount of Damage:</strong> 8</li>", "<li><strong>Fortitude:</strong> 8</li>"]}, {"name": ["<strong>Stagger TB</strong>"], "effect": ["<p></p>"], "attributes": ["<li><strong>Card Type:</strong> Action</li>", "<li><strong>Collector's Number:</strong> 65</li>", "<li><strong>Rarity:</strong> Uncommon</li>", "<li><strong>Amount of Damage:</strong> 0</li>", "<li><strong>Fortitude:</strong> 3</li>"]}, {"name": ["<strong>Standing Drop Kick TB</strong>"], "effect": ["<p></p>"], "attributes": ["<li><strong>Card Type:</strong> Strike</li>", "<li><strong>Collector's Number:</strong> 11</li>", "<li><strong>Rarity:</strong> Common</li>", "<li><strong>Amount of Damage:</strong> 8</li>", "<li><strong>Fortitude:</strong> 8</li>"]}, {"name": ["<strong>Super Masks and Super Capes</strong>"], "effect": ["<p>Hurri-Friends</p>"], "attributes": ["<li><strong>Card Type:</strong> Backstage Area</li>", "<li><strong>Collector's Number:</strong> 156</li>", "<li><strong>Rarity:</strong> Premium Rare</li>"]}, {"name": ["<strong>Super Storm Front</strong>"], "effect": ["<p>Hurri-Friends </p>", "<p><em>Mid-Match Strike + High Risk</em></p>"], "attributes": ["<li><strong>Card Type:</strong> Mid-match Strike</li>", "<li><strong>Collector's Number:</strong> 157</li>", "<li><strong>Rarity:</strong> Premium Rare</li>", "<li><strong>Amount of Damage:</strong> 20</li>", "<li><strong>Fortitude:</strong> 20</li>"]}, {"name": ["<strong>Swinging Neck Breaker</strong>"], "effect": ["<p></p>"], "attributes": ["<li><strong>Card Type:</strong> Grapple</li>", "<li><strong>Collector's Number:</strong> 30</li>", "<li><strong>Rarity:</strong> Uncommon</li>", "<li><strong>Amount of Damage:</strong> 8</li>", "<li><strong>Fortitude:</strong> 7</li>"]}, {"name": ["<strong>Temecula, California</strong>"], "effect": ["<p>Christy</p>"], "attributes": ["<li><strong>Card Type:</strong> Pre-Match Venue</li>", "<li><strong>Collector's Number:</strong> 113</li>", "<li><strong>Rarity:</strong> Ultra Rare</li>", "<li><strong>Amount of Damage:</strong> 0</li>", "<li><strong>Fortitude:</strong> 0</li>"]}, {"name": ["<strong>That's How I Roll</strong>"], "effect": ["<p>Christian / Edge</p>"], "attributes": ["<li><strong>Card Type:</strong> Action</li>", "<li><strong>Collector's Number:</strong> 109</li>", "<li><strong>Rarity:</strong> Exclusive</li>", "<li><strong>Amount of Damage:</strong> 0</li>", "<li><strong>Fortitude:</strong> 0</li>"]}, {"name": ["<strong>That's It</strong>"], "effect": ["<p></p>"], "attributes": ["<li><strong>Card Type:</strong> Action</li>", "<li><strong>Collector's Number:</strong> 67</li>", "<li><strong>Rarity:</strong> Uncommon</li>", "<li><strong>Amount of Damage:</strong> 0</li>", "<li><strong>Fortitude:</strong> 30</li>"]}, {"name": ["<strong>The Animal</strong>"], "effect": ["<p>Batista</p>"], "attributes": ["<li><strong>Card Type:</strong> Reversal</li>", "<li><strong>Collector's Number:</strong> 103</li>", "<li><strong>Rarity:</strong> Exclusive</li>", "<li><strong>Amount of Damage:</strong> 0</li>", "<li><strong>Fortitude:</strong> 6</li>"]}, {"name": ["<strong>The Christian Coalition</strong>"], "effect": ["<p>Christian</p>"], "attributes": ["<li><strong>Card Type:</strong> Action</li>", "<li><strong>Collector's Number:</strong> 110</li>", "<li><strong>Rarity:</strong> Exclusive</li>", "<li><strong>Amount of Damage:</strong> 0</li>", "<li><strong>Fortitude:</strong> 5</li>"]}, {"name": ["<strong>The Destroyer</strong>"], "effect": ["<p>Batista</p>"], "attributes": ["<li><strong>Card Type:</strong> Pre-match Event</li>", "<li><strong>Collector's Number:</strong> 101</li>", "<li><strong>Rarity:</strong> Ultra Rare</li>", "<li><strong>Amount of Damage:</strong> 0</li>", "<li><strong>Fortitude:</strong> 0</li>"]}, {"name": ["<strong>The GM of Stevie Night Heat</strong>"], "effect": ["<p></p>"], "attributes": ["<li><strong>Card Type:</strong> Mid-match Action</li>", "<li><strong>Collector's Number:</strong> 89</li>", "<li><strong>Rarity:</strong> Common</li>", "<li><strong>Amount of Damage:</strong> 0</li>", "<li><strong>Fortitude:</strong> 0</li>"]}, {"name": ["<strong>The Hidden Dragon: Balance</strong>"], "effect": ["<p>RVD</p>"], "attributes": ["<li><strong>Card Type:</strong> Pre-match Event</li>", "<li><strong>Collector's Number:</strong> 172</li>", "<li><strong>Rarity:</strong> Premium Rare</li>", "<li><strong>Amount of Damage:</strong> 0</li>", "<li><strong>Fortitude:</strong> 0</li>"]}, {"name": ["<strong>The Hurri-Friends Armory</strong>"], "effect": ["<p>Hurri-Friends</p>"], "attributes": ["<li><strong>Card Type:</strong> Pre-Match Venue</li>", "<li><strong>Collector's Number:</strong> 155</li>", "<li><strong>Rarity:</strong> Ultra Rare</li>", "<li><strong>Amount of Damage:</strong> 0</li>", "<li><strong>Fortitude:</strong> 0</li>"]}, {"name": ["<strong>The Mack Militant</strong>"], "effect": ["<p>Teddy Long</p>"], "attributes": ["<li><strong>Card Type:</strong> Action</li>", "<li><strong>Collector's Number:</strong> 135</li>", "<li><strong>Rarity:</strong> Exclusive</li>", "<li><strong>Amount of Damage:</strong> 0</li>", "<li><strong>Fortitude:</strong> 5</li>"]}, {"name": ["<strong>The MaTrish Move</strong>"], "effect": ["<p>Trish Stratus</p>"], "attributes": ["<li><strong>Card Type:</strong> Reversal</li>", "<li><strong>Collector's Number:</strong> 176</li>", "<li><strong>Rarity:</strong> Premium Rare</li>", "<li><strong>Amount of Damage:</strong> 0</li>", "<li><strong>Fortitude:</strong> 0</li>"]}, {"name": ["<strong>The Old Switcheroo</strong>"], "effect": ["<p></p>"], "attributes": ["<li><strong>Card Type:</strong> Pre-match Event</li>", "<li><strong>Collector's Number:</strong> 87</li>", "<li><strong>Rarity:</strong> Rare</li>", "<li><strong>Amount of Damage:</strong> 0</li>", "<li><strong>Fortitude:</strong> 0</li>"]}, {"name": ["<strong>The Power of the Punch</strong>"], "effect": ["<p>William Regal</p>"], "attributes": ["<li><strong>Card Type:</strong> Mid-match Action</li>", "<li><strong>Collector's Number:</strong> 174</li>", "<li><strong>Rarity:</strong> Premium Rare</li>", "<li><strong>Amount of Damage:</strong> 0</li>", "<li><strong>Fortitude:</strong> 0</li>"]}, {"name": ["<strong>The Snapshot</strong>"], "effect": ["<p>MNM</p>"], "attributes": ["<li><strong>Card Type:</strong> Trademark Finisher</li>", "<li><strong>Collector's Number:</strong> 149</li>", "<li><strong>Rarity:</strong> Ultra Rare</li>", "<li><strong>Amount of Damage:</strong> 30</li>", "<li><strong>Fortitude:</strong> 30</li>"]}, {"name": ["<strong>The Wolverine's Sharpshooter</strong>"], "effect": ["<p>Chris Benoit </p>", "<p><em>Submission / Action</em></p>"], "attributes": ["<li><strong>Card Type:</strong> Submission</li>", "<li><strong>Collector's Number:</strong> 166</li>", "<li><strong>Rarity:</strong> Premium Rare</li>", "<li><strong>Amount of Damage:</strong> 14</li>", "<li><strong>Fortitude:</strong> 16</li>"]}, {"name": ["<strong>There's Nothing Sweeter</strong>"], "effect": ["<p>MNM</p>"], "attributes": ["<li><strong>Card Type:</strong> Action</li>", "<li><strong>Collector's Number:</strong> 151</li>", "<li><strong>Rarity:</strong> Premium Rare</li>", "<li><strong>Amount of Damage:</strong> 0</li>", "<li><strong>Fortitude:</strong> 5</li>"]}, {"name": ["<strong>This is Just the Beginning</strong>"], "effect": ["<p></p>"], "attributes": ["<li><strong>Card Type:</strong> Mid-match Action</li>", "<li><strong>Collector's Number:</strong> 90</li>", "<li><strong>Rarity:</strong> Common</li>", "<li><strong>Amount of Damage:</strong> 1</li>", "<li><strong>Fortitude:</strong> 0</li>"]}, {"name": ["<strong>Thuggin' &amp; Buggin'</strong>"], "effect": ["<p>Teddy Long</p>"], "attributes": ["<li><strong>Card Type:</strong> Action</li>", "<li><strong>Collector's Number:</strong> 134</li>", "<li><strong>Rarity:</strong> Exclusive</li>", "<li><strong>Amount of Damage:</strong> 0</li>", "<li><strong>Fortitude:</strong> 0</li>"]}, {"name": ["<strong>Tomakazi DDT</strong>"], "effect": ["<p>Christian</p>"], "attributes": ["<li><strong>Card Type:</strong> Grapple / Special</li>", "<li><strong>Collector's Number:</strong> 111</li>", "<li><strong>Rarity:</strong> Exclusive</li>", "<li><strong>Amount of Damage:</strong> 14</li>", "<li><strong>Fortitude:</strong> 11</li>"]}, {"name": ["<strong>Tornado DDT TB</strong>"], "effect": ["<p></p>"], "attributes": ["<li><strong>Card Type:</strong> Grapple</li>", "<li><strong>Collector's Number:</strong> 37</li>", "<li><strong>Rarity:</strong> Rare</li>", "<li><strong>Amount of Damage:</strong> 13</li>", "<li><strong>Fortitude:</strong> 7</li>"]}, {"name": ["<strong>Torture Rack TB</strong>"], "effect": ["<p><em>Submission / Action</em></p>"], "attributes": ["<li><strong>Card Type:</strong> Submission</li>", "<li><strong>Collector's Number:</strong> 53</li>", "<li><strong>Rarity:</strong> Rare</li>", "<li><strong>Amount of Damage:</strong> 14</li>", "<li><strong>Fortitude:</strong> 11</li>"]}, {"name": ["<strong>Trash Talkin' Interview TB</strong>"], "effect": ["<p></p>"], "attributes": ["<li><strong>Card Type:</strong> Pre-match Feud</li>", "<li><strong>Collector's Number:</strong> 78</li>", "<li><strong>Rarity:</strong> Common</li>", "<li><strong>Amount of Damage:</strong> 0</li>", "<li><strong>Fortitude:</strong> 0</li>"]}, {"name": ["<strong>Uncle Eric's Karate Kick</strong>"], "effect": ["<p>Eric Bischoff </p>", "<p><em>Strike / Strike / Special</em></p>"], "attributes": ["<li><strong>Card Type:</strong> Strike / Special</li>", "<li><strong>Collector's Number:</strong> 181</li>", "<li><strong>Rarity:</strong> Premium Rare</li>", "<li><strong>Amount of Damage:</strong> 5</li>", "<li><strong>Fortitude:</strong> 5</li>"]}, {"name": ["<strong>Unleash Hell</strong>"], "effect": ["<p>Stone Cold Steve Austin</p>"], "attributes": ["<li><strong>Card Type:</strong> Action</li>", "<li><strong>Collector's Number:</strong> 160</li>", "<li><strong>Rarity:</strong> Premium Rare</li>", "<li><strong>Amount of Damage:</strong> 0</li>", "<li><strong>Fortitude:</strong> 16</li>"]}, {"name": ["<strong>Viva Las Divas</strong>"], "effect": ["<p></p>"], "attributes": ["<li><strong>Card Type:</strong> Action + Action</li>", "<li><strong>Collector's Number:</strong> 59</li>", "<li><strong>Rarity:</strong> Common</li>", "<li><strong>Amount of Damage:</strong> 0</li>", "<li><strong>Fortitude:</strong> 0</li>"]}, {"name": ["<strong>Want to Take My Test?</strong>"], "effect": ["<p>Torrie Wilson</p>"], "attributes": ["<li><strong>Card Type:</strong> Action</li>", "<li><strong>Collector's Number:</strong> 185</li>", "<li><strong>Rarity:</strong> Premium Rare</li>", "<li><strong>Amount of Damage:</strong> 0</li>", "<li><strong>Fortitude:</strong> 9</li>"]}, {"name": ["<strong>When I Get You Alone</strong>"], "effect": ["<p>Lita</p>"], "attributes": ["<li><strong>Card Type:</strong> Action</li>", "<li><strong>Collector's Number:</strong> 171</li>", "<li><strong>Rarity:</strong> Premium Rare</li>", "<li><strong>Amount of Damage:</strong> 0</li>", "<li><strong>Fortitude:</strong> 0</li>"]}, {"name": ["<strong>When You Run the Show, You Make the Rules</strong>"], "effect": ["<p></p>"], "attributes": ["<li><strong>Card Type:</strong> Mid-match Action</li>", "<li><strong>Collector's Number:</strong> 188</li>", "<li><strong>Rarity:</strong> Premium Rare</li>", "<li><strong>Amount of Damage:</strong> 0</li>", "<li><strong>Fortitude:</strong> 12</li>"]}, {"name": ["<strong>Who Wants to be My Friend?</strong>"], "effect": ["<p>Heidenreich</p>"], "attributes": ["<li><strong>Card Type:</strong> Action / Reversal</li>", "<li><strong>Collector's Number:</strong> 139</li>", "<li><strong>Rarity:</strong> Premium Rare</li>", "<li><strong>Amount of Damage:</strong> 0</li>", "<li><strong>Fortitude:</strong> 15</li>"]}, {"name": ["<strong>Who's Cooler than Michelle McCool?</strong>"], "effect": ["<p></p>"], "attributes": ["<li><strong>Card Type:</strong> Pre-match Event</li>", "<li><strong>Collector's Number:</strong> 79</li>", "<li><strong>Rarity:</strong> Common</li>", "<li><strong>Amount of Damage:</strong> 0</li>", "<li><strong>Fortitude:</strong> 0</li>"]}, {"name": ["<strong>Workin' on the Knee TB</strong>"], "effect": ["<p></p>"], "attributes": ["<li><strong>Card Type:</strong> Grapple + Submission</li>", "<li><strong>Collector's Number:</strong> 38</li>", "<li><strong>Rarity:</strong> Rare</li>", "<li><strong>Amount of Damage:</strong> 10</li>", "<li><strong>Fortitude:</strong> 7</li>"]}, {"name": ["<strong>Wrist Breaker</strong>"], "effect": ["<p></p>"], "attributes": ["<li><strong>Card Type:</strong> Submission</li>", "<li><strong>Collector's Number:</strong> 45</li>", "<li><strong>Rarity:</strong> Uncommon</li>", "<li><strong>Amount of Damage:</strong> 6</li>", "<li><strong>Fortitude:</strong> 2</li>"]}, {"name": ["<strong>WWE Divas Rule!</strong>"], "effect": ["<p></p>"], "attributes": ["<li><strong>Card Type:</strong> Mid-match Action</li>", "<li><strong>Collector's Number:</strong> 95</li>", "<li><strong>Rarity:</strong> Uncommon</li>", "<li><strong>Amount of Damage:</strong> 0</li>", "<li><strong>Fortitude:</strong> 25</li>"]}, {"name": ["<strong>WWE Divas: the Next Generation</strong>"], "effect": ["<p></p>"], "attributes": ["<li><strong>Card Type:</strong> Mid-match Action / Action</li>", "<li><strong>Collector's Number:</strong> 93</li>", "<li><strong>Rarity:</strong> Uncommon</li>", "<li><strong>Amount of Damage:</strong> 0</li>", "<li><strong>Fortitude:</strong> 0</li>"]}, {"name": ["<strong>You Can't Spell \"Funaki\" Without F-U-N</strong>"], "effect": ["<p></p>"], "attributes": ["<li><strong>Card Type:</strong> Pre-match Event</li>", "<li><strong>Collector's Number:</strong> 83</li>", "<li><strong>Rarity:</strong> Uncommon</li>", "<li><strong>Amount of Damage:</strong> 0</li>", "<li><strong>Fortitude:</strong> 0</li>"]}, {"name": ["<strong>You Have Tasty Toes</strong>"], "effect": ["<p>Gene Snitsky</p>"], "attributes": ["<li><strong>Card Type:</strong> Action</li>", "<li><strong>Collector's Number:</strong> 144</li>", "<li><strong>Rarity:</strong> Premium Rare</li>", "<li><strong>Amount of Damage:</strong> 0</li>", "<li><strong>Fortitude:</strong> 10</li>"]}, {"name": ["<strong>You Knew it Would End This Way...</strong>"], "effect": ["<p></p>"], "attributes": ["<li><strong>Card Type:</strong> Mid-match Action</li>", "<li><strong>Collector's Number:</strong> 91</li>", "<li><strong>Rarity:</strong> Common</li>", "<li><strong>Amount of Damage:</strong> 0</li>", "<li><strong>Fortitude:</strong> 20</li>"]}, {"name": ["<strong>Your Freaking Hero or John Cena?</strong>"], "effect": ["<p></p>"], "attributes": ["<li><strong>Card Type:</strong> Smackdown Enforcer</li>", "<li><strong>Collector's Number:</strong> 133</li>", "<li><strong>Rarity:</strong> Exclusive</li>"]}]}